basic/__deps_.py
basic/__init__.py
basic/cetLam.py
basic/chrLam.py
basic/conLam.py
basic/conLas_ucd_old.py
basic/decLam.py
basic/depLam.py
basic/insLas.py
basic/itrLam.py
basic/metLas.py
basic/nymLas.py
basic/parLam.py
basic/parLam_ucd_old.py
basic/proces.py
basic/setLam.py
basic/timeit.py
basic/tstLas.py
basic/tyeLas.py
basic/typLam.py
basic/typLas.py
muti.basic-0.14.69.dist-info/LICENSE
muti.basic-0.14.69.dist-info/METADATA
muti.basic-0.14.69.dist-info/WHEEL
muti.basic-0.14.69.dist-info/top_level.txt
muti.basic-0.14.69.dist-info/RECORD
