Metadata-Version: 2.1
Name: muti.basic
Version: 0.14.69
Summary: muti for python
Home-page: https://github.com/E-C-Ares/muti.basic
Author: E.C.Ares
Author-email: E.C.Ares@outlook.com
Classifier: Programming Language :: Python :: 3.10
Classifier: Programming Language :: Python :: 3.11
Classifier: Programming Language :: Python :: 3.12
Classifier: License :: OSI Approved :: MIT License
Classifier: Operating System :: OS Independent
License-File: LICENSE
